lisa/artifacts/__init__.py
lisa/artifacts/manifest.py
lisa_artifacts-0.4.0.dist-info/licenses/LICENSE
lisa_artifacts-0.4.0.dist-info/METADATA
lisa_artifacts-0.4.0.dist-info/WHEEL
lisa_artifacts-0.4.0.dist-info/top_level.txt
lisa_artifacts-0.4.0.dist-info/RECORD
