Metadata-Version: 2.4
Name: lisa-artifacts
Version: 0.4.0
Summary: A library for managing object storage artifacts
License-Expression: Apache-2.0
Project-URL: Homepage, https://github.com/lisa-sgs/artifacts
Project-URL: Source, https://github.com/lisa-sgs/artifacts
Project-URL: Issues, https://github.com/lisa-sgs/artifacts/issues
Project-URL: Documentation, https://lisa-sgs.github.io/artifacts/
Project-URL: Changelog, https://github.com/lisa-sgs/artifacts/blob/main/CHANGELOG.md
Requires-Python: >=3.11
License-File: LICENSE
Requires-Dist: boto3
Requires-Dist: pydantic
Requires-Dist: types-boto3[s3]
Dynamic: license-file
